{
  "version": 1,
  "updated_at": "2025-01-01",
  "default_country": "US",
  "categories": [
    { "key": "electronics", "label": "Electronics" },
    { "key": "fashion", "label": "Fashion" },
    { "key": "beauty", "label": "Beauty" },
    { "key": "courses", "label": "Courses" },
    { "key": "tools", "label": "Tools" }
  ],
  "items": [
    {
      "id": "realme_wireless_earbuds",
      "category": "electronics",
      "countries": ["IN"],
      "title": "Wireless Bluetooth Earbuds",
      "description": "Lightweight earbuds with long playtime and water resistance",
      "image": "",
      "discountPercent": 35,
      "links": {
        "IN": "https://www.amazon.in/realme-Wireless-Playtime-Resistant-SlateGrey/dp/B0F5GV3Y87?linkCode=ll1&tag=1729010-21"
      }
    },
    {
      "id": "cotton_ankle_socks",
      "category": "fashion",
      "countries": ["IN"],
      "title": "Cotton Ankle Socks (Pack)",
      "description": "Comfortable daily-wear ankle socks made from soft cotton",
      "image": "",
      "discountPercent": 25,
      "links": {
        "IN": "https://www.amazon.in/SWAGR-Pairs-Solid-Cotton-Ankle/dp/B0DC14CYKR?linkCode=ll1&tag=1729010-21"
      }
    },
    {
      "id": "ghost_eye_novel",
      "category": "courses",
      "countries": ["IN"],
      "title": "The Ghost’s Eye (Novel)",
      "description": "A compelling literary work by Amitav Ghosh",
      "image": "",
      "links": {
        "IN": "https://www.amazon.in/Ghost-eye-Novel-Amitav-Ghosh/dp/9373073435?linkCode=ll1&tag=1729010-21"
      }
    },
    {
      "id": "men_puffer_jacket",
      "category": "fashion",
      "countries": ["IN"],
      "title": "Men’s Puffer Jacket",
      "description": "Warm, lightweight winter jacket for everyday wear",
      "image": "",
      "discountPercent": 40,
      "links": {
        "IN": "https://www.amazon.in/Ben-Martin-Standard-Length-Puffer/dp/B0DK7J97TH?linkCode=ll1&tag=1729010-21"
      }
    },
    {
      "id": "thermal_label_printer",
      "category": "tools",
      "countries": ["US"],
      "title": "Thermal Shipping Label Printer",
      "description": "High-speed thermal printer for shipping labels",
      "image": "",
      "discountPercent": 30,
      "links": {
        "US": "https://www.amazon.com/ORGSTA-Thermal-Shipping-Label-Printer/dp/B0D3WYW4CR?linkCode=ll1&tag=18280e7-20"
      }
    },
    {
      "id": "smart_meat_thermometer",
      "category": "electronics",
      "countries": ["US"],
      "title": "Wireless Meat Thermometer",
      "description": "Smart thermometer for precise cooking and grilling",
      "image": "",
      "links": {
        "US": "https://www.amazon.com/New-MEATER-Plus-Thermometer-Lab-Certified/dp/B0CP8BPXKR?linkCode=ll1&tag=18280e7-20"
      }
    },
    {
      "id": "rechargeable_hand_warmer",
      "category": "electronics",
      "countries": ["US"],
      "title": "Rechargeable Hand Warmer",
      "description": "Portable electric hand warmer with real-time temperature",
      "image": "",
      "discountPercent": 20,
      "links": {
        "US": "https://www.amazon.com/Hotdot-Rechargeable-104-131F-Real-Time-Electric/dp/B0FNNDWM4S?linkCode=ll1&tag=18280e7-20"
      }
    },
    {
      "id": "lg_lightweight_laptop",
      "category": "electronics",
      "countries": ["US"],
      "title": "LG Lightweight Laptop (15-inch)",
      "description": "Portable laptop with modern processor and sleek design",
      "image": "",
      "links": {
        "US": "https://www.amazon.com/LG-15-inch-Lightweight-Processor-Obsidian/dp/B0F7S913CQ?linkCode=ll1&tag=18280e7-20"
      }
    },
    {
      "id": "toilet_paper_pack",
      "category": "tools",
      "countries": ["US"],
      "title": "Amazon Basics Toilet Paper",
      "description": "Soft, strong 2-ply toilet paper for everyday use",
      "image": "",
      "discountPercent": 15,
      "links": {
        "US": "https://www.amazon.com/Amazon-Basics-2-Ply-Toilet-Paper/dp/B095CN96JS?linkCode=ll1&tag=18280e7-20"
      }
    },
    {
      "id": "shipping_labels_fanfold",
      "category": "tools",
      "countries": ["US"],
      "title": "Fanfold Shipping Labels",
      "description": "Perforated fanfold labels for shipping and logistics",
      "image": "",
      "links": {
        "US": "https://www.amazon.com/9527-Product-Fanfold-Perforated-Shipping/dp/B082183BM6?linkCode=ll1&tag=18280e7-20"
      }
    },
    {
      "id": "hair_shine_serum",
      "category": "beauty",
      "countries": ["US"],
      "title": "Nourishing Hair Shine Serum",
      "description": "High-shine, cruelty-free hair serum for smooth finish",
      "image": "https://sanjeet01729.github.io/omnisearch-assets/images/beauty/Glow%20Reviver%20Lip%20Oil,%20Nourishing%20Tinted%20Lip%20Oil%20For%20A%20High-shine%20Finish,%20Infused%20With%20Jojoba%20Oil,%20Vegan%20&%20Cruelty-free,%20Rose%20Envy.png",
      "discountPercent": 28,
      "links": {
        "US": "https://www.amazon.com/l-f-Reviver-Nourishing-High-shine-Cruelty-free/dp/B0CMJZ8G6Y?linkCode=ll1&tag=18280e7-20"
      }
    }
  ]
}
